example_package/__init__.py
example_package/example.py
sparrow_order_lib_pkg-0.0.1.dist-info/LICENSE
sparrow_order_lib_pkg-0.0.1.dist-info/METADATA
sparrow_order_lib_pkg-0.0.1.dist-info/WHEEL
sparrow_order_lib_pkg-0.0.1.dist-info/top_level.txt
sparrow_order_lib_pkg-0.0.1.dist-info/RECORD
