Metadata-Version: 2.1
Name: sparrow-order-lib-pkg
Version: 0.0.1
Summary: This is a lib for sparrow order projects.
Home-page: https://github.com/pypa/sampleproject
Author: Jessica Liao
Author-email: 18610193367@sina.cn
License: UNKNOWN
Project-URL: Bug Tracker, https://github.com/pypa/sampleproject/issues
Platform: UNKNOWN
Classifier: Programming Language :: Python :: 3
Classifier: License :: OSI Approved :: MIT License
Classifier: Operating System :: OS Independent
Requires-Python: >=3.7
License-File: LICENSE
